digifinex/__init__.py
digifinex/digifinex.py
digifinex/error_codes.py
python_digifinex-0.0.3.dist-info/LICENSE
python_digifinex-0.0.3.dist-info/METADATA
python_digifinex-0.0.3.dist-info/WHEEL
python_digifinex-0.0.3.dist-info/top_level.txt
python_digifinex-0.0.3.dist-info/RECORD
