Metadata-Version: 2.1
Name: python-digifinex
Version: 0.0.3
Summary: Digifinex APIs in Python
Home-page: https://github.com/abhisek1985/python-digifinex
Author: Abhisek Roy
Author-email: abhisekroy.cse@gmail.com
License: UNKNOWN
Platform: UNKNOWN
Classifier: Programming Language :: Python :: 3
Classifier: Programming Language :: Python :: 2
Classifier: License :: OSI Approved :: MIT License
Classifier: Operating System :: OS Independent
